{
  "version": "1.1.1",
  "windows": {
    "main": {
      "main": true,
      "url": "app://editor/index.html",
      "windowType": "dockable",
      "x": 0,
      "y": 23,
      "width": 1440,
      "height": 829,
      "layout": {
        "children": [
          {
            "children": [
              {
                "active": 0,
                "children": [
                  "hierarchy"
                ],
                "height": 373.78125,
                "type": "panel",
                "width": 232.765625
              },
              {
                "active": 0,
                "children": [
                  "assets"
                ],
                "height": 361.21875,
                "type": "panel",
                "width": 232.765625
              }
            ],
            "height": 738,
            "type": "dock-v",
            "width": 232.765625
          },
          {
            "children": [
              {
                "children": [
                  {
                    "active": 0,
                    "children": [
                      "scene"
                    ],
                    "height": 443.65625,
                    "type": "panel",
                    "width": 590.703125
                  },
                  {
                    "active": 0,
                    "children": [
                      "node-library"
                    ],
                    "height": 443.65625,
                    "type": "panel",
                    "width": 224.328125
                  }
                ],
                "height": 443.65625,
                "type": "dock-h",
                "width": 818.03125
              },
              {
                "active": 1,
                "children": [
                  "console",
                  "timeline"
                ],
                "height": 291.328125,
                "type": "panel",
                "width": 818.03125
              }
            ],
            "height": 738,
            "type": "dock-v",
            "width": 818.03125
          },
          {
            "active": 0,
            "children": [
              "inspector"
            ],
            "height": 738,
            "type": "panel",
            "width": 377.203125
          }
        ],
        "type": "dock-h"
      },
      "panels": [
        "node-library",
        "console",
        "timeline",
        "inspector",
        "hierarchy",
        "assets",
        "scene"
      ]
    }
  },
  "panels": {
    "project-settings": {
      "x": 662,
      "y": 246,
      "width": 600,
      "height": 564
    },
    "preferences": {
      "x": 672,
      "y": 246,
      "width": 739,
      "height": 564
    },
    "builder": {
      "x": 702,
      "y": 146,
      "width": 516,
      "height": 738
    }
  }
}